{"batch_size": 4, "context_factor": 5, "context_len": 197, "dropout": 0.30833021591584964, "gradient_clipping": 4, "group_by_weeks": true, "hidden_units": 50, "kernel_size": 11, "learning_rate": 0.0009935134369950666, "loss_function": "RMSELoss", "lstm": "multivariate", "model": "GRU", "models_to_select": 5, "momentum": 0.9546047336361664, "n_days": 4, "normalization": {"general_treatment": {"group_by_weeks": true, "leave_outliers": true, "log": true, "remove_seasonality": false, "remove_trend": false}, "transformer": "MinMaxScaler", "treatment": "static"}, "normalize_all": "False", "num_epochs": 1, "num_features": 15, "num_filters": 16, "num_layers": 1, "optimizer": "Adam", "prime_hidden": "True", "reuse_hidden_state": "True", "sarima": {"D_param": 1, "P_param": 2, "Q_param": 1, "d_param": 0, "m_param": 4, "p_param": 2, "q_param": 0, "t_param": "n"}, "seq_length": 50, "stateful": false, "step": 1, "ticker": "SPY", "train_on": "current_ticker", "train_ratio": 0.52, "training": "alternate", "trend_degree": 2, "trend_type": "additive", "use_dataloader": true, "val_ratio": 0.12, "variable_context_size": true, "weight_decay": 0.0007588855009923604, "xgboost": {"colsample_bytree": 0.5, "gamma": 0.1, "learning_rate_x": 0.2, "max_depth": 15, "n_estimators": 50, "objective": "reg:squarederror", "random_state": 42, "reg_alpha": 0.1, "reg_lambda": 3, "subsample": 0.8}}